pkrcomponents/__init__.py
pkrcomponents/components/__init__.py
pkrcomponents/components/actions/__init__.py
pkrcomponents/components/actions/action.py
pkrcomponents/components/actions/action_move.py
pkrcomponents/components/actions/actions_history.py
pkrcomponents/components/actions/actions_sequence.py
pkrcomponents/components/actions/blind_type.py
pkrcomponents/components/actions/posting.py
pkrcomponents/components/actions/street.py
pkrcomponents/components/cards/__init__.py
pkrcomponents/components/cards/bitcard.py
pkrcomponents/components/cards/card.py
pkrcomponents/components/cards/combo.py
pkrcomponents/components/cards/deck.py
pkrcomponents/components/cards/evaluator.py
pkrcomponents/components/cards/flop.py
pkrcomponents/components/cards/hand.py
pkrcomponents/components/cards/lookup_table.py
pkrcomponents/components/cards/rank.py
pkrcomponents/components/cards/shape.py
pkrcomponents/components/cards/suit.py
pkrcomponents/components/cards/utils/__init__.py
pkrcomponents/components/cards/utils/converters.py
pkrcomponents/components/players/__init__.py
pkrcomponents/components/players/player_hand_stats.py
pkrcomponents/components/players/players.py
pkrcomponents/components/players/position.py
pkrcomponents/components/players/positions_map.py
pkrcomponents/components/players/table_player.py
pkrcomponents/components/players/datafields/__init__.py
pkrcomponents/components/players/datafields/general.py
pkrcomponents/components/players/datafields/postflop.py
pkrcomponents/components/players/datafields/preflop.py
pkrcomponents/components/players/street_hand_stats/__init__.py
pkrcomponents/components/players/street_hand_stats/base.py
pkrcomponents/components/players/street_hand_stats/general.py
pkrcomponents/components/players/street_hand_stats/postflop.py
pkrcomponents/components/players/street_hand_stats/preflop.py
pkrcomponents/components/tables/__init__.py
pkrcomponents/components/tables/board.py
pkrcomponents/components/tables/pot.py
pkrcomponents-4.5.0.dist-info/LICENSE.txt
pkrcomponents-4.5.0.dist-info/METADATA
pkrcomponents-4.5.0.dist-info/WHEEL
pkrcomponents-4.5.0.dist-info/top_level.txt
pkrcomponents-4.5.0.dist-info/RECORD
